{
    "nodes": [
        {
            "id": "495623",
            "name": "Oscar    ",
            "group": 1,
            "neighbor_number": 3,
            "neighbor_distance": 0
        },
        {
            "id": "495625",
            "name": "Saul Schaffer   ",
            "group": 1,
            "neighbor_number": 7,
            "neighbor_distance": 1
        },
        {
            "id": "9928",
            "name": "Atsuo Takanishi   ",
            "group": 1,
            "neighbor_number": 35,
            "neighbor_distance": 1
        },
        {
            "id": "317470",
            "name": "Melissa Castine   ",
            "group": 1,
            "neighbor_number": 19,
            "neighbor_distance": 1
        },
        {
            "id": "2759896",
            "name": "Asa T. Furman   ",
            "group": 1,
            "neighbor_number": 6,
            "neighbor_distance": 2
        },
        {
            "id": "1842131",
            "name": "Bernhard Thom   ",
            "group": 1,
            "neighbor_number": 6,
            "neighbor_distance": 2
        },
        {
            "id": "1025197",
            "name": "Daniel Homocianu   ",
            "group": 1,
            "neighbor_number": 6,
            "neighbor_distance": 2
        },
        {
            "id": "1022134",
            "name": "Takuya Ehiro   ",
            "group": 1,
            "neighbor_number": 8,
            "neighbor_distance": 2
        },
        {
            "id": "794",
            "name": "Jos   ",
            "group": 1,
            "neighbor_number": 1682,
            "neighbor_distance": 2
        },
        {
            "id": "1866710",
            "name": "Sarbani Mishra   ",
            "group": 1,
            "neighbor_number": 8,
            "neighbor_distance": 2
        },
        {
            "id": "959734",
            "name": "Jian-Sheng Chen   ",
            "group": 1,
            "neighbor_number": 8,
            "neighbor_distance": 2
        },
        {
            "id": "401461",
            "name": "Rafael Castro   ",
            "group": 1,
            "neighbor_number": 6,
            "neighbor_distance": 2
        },
        {
            "id": "2142075",
            "name": "M. H. J. Webb   ",
            "group": 1,
            "neighbor_number": 6,
            "neighbor_distance": 2
        },
        {
            "id": "401460",
            "name": "Dror Rubinstein   ",
            "group": 1,
            "neighbor_number": 11,
            "neighbor_distance": 2
        },
        {
            "id": "2142074",
            "name": "H. G. M. Pullen   ",
            "group": 1,
            "neighbor_number": 6,
            "neighbor_distance": 2
        },
        {
            "id": "3158208",
            "name": "Namrata Meharwal   ",
            "group": 1,
            "neighbor_number": 8,
            "neighbor_distance": 2
        },
        {
            "id": "2142073",
            "name": "Zeynep Engin   ",
            "group": 1,
            "neighbor_number": 8,
            "neighbor_distance": 2
        },
        {
            "id": "1068244",
            "name": "Ingrid J. Pickering   ",
            "group": 1,
            "neighbor_number": 7,
            "neighbor_distance": 2
        },
        {
            "id": "2068750",
            "name": "Yul Ha   ",
            "group": 1,
            "neighbor_number": 24,
            "neighbor_distance": 2
        },
        {
            "id": "2617379",
            "name": "Sergiy V. Filatov   ",
            "group": 1,
            "neighbor_number": 8,
            "neighbor_distance": 2
        },
        {
            "id": "2142072",
            "name": "D. V. Cheesman   ",
            "group": 1,
            "neighbor_number": 6,
            "neighbor_distance": 2
        },
        {
            "id": "214702",
            "name": "Hai Yu 0003   ",
            "group": 1,
            "neighbor_number": 20,
            "neighbor_distance": 2
        },
        {
            "id": "355682",
            "name": "Joseph Djugash   ",
            "group": 1,
            "neighbor_number": 9,
            "neighbor_distance": 2
        },
        {
            "id": "2142071",
            "name": "D. Marudhadevi   ",
            "group": 1,
            "neighbor_number": 6,
            "neighbor_distance": 2
        },
        {
            "id": "2811112",
            "name": "Kenfack Blanchard   ",
            "group": 1,
            "neighbor_number": 8,
            "neighbor_distance": 2
        },
        {
            "id": "9884",
            "name": "Paolo Dario   ",
            "group": 1,
            "neighbor_number": 17,
            "neighbor_distance": 2
        },
        {
            "id": "1842202",
            "name": "O. Schoen   ",
            "group": 1,
            "neighbor_number": 7,
            "neighbor_distance": 2
        },
        {
            "id": "498011",
            "name": "Adam Rogalewicz   ",
            "group": 1,
            "neighbor_number": 13,
            "neighbor_distance": 2
        },
        {
            "id": "117194",
            "name": "Md. Saiful Islam   ",
            "group": 1,
            "neighbor_number": 13,
            "neighbor_distance": 2
        },
        {
            "id": "545381",
            "name": "Medhat Mohamad   ",
            "group": 1,
            "neighbor_number": 18,
            "neighbor_distance": 2
        },
        {
            "id": "354617",
            "name": "Jonghoek Kim   ",
            "group": 1,
            "neighbor_number": 12,
            "neighbor_distance": 2
        },
        {
            "id": "1022035",
            "name": "Reyes Tatsuru Shiroku   ",
            "group": 1,
            "neighbor_number": 7,
            "neighbor_distance": 2
        },
        {
            "id": "1761990",
            "name": "Claudio A. Bonilla   ",
            "group": 1,
            "neighbor_number": 8,
            "neighbor_distance": 2
        },
        {
            "id": "1866712",
            "name": "Amir A. Shah   ",
            "group": 1,
            "neighbor_number": 8,
            "neighbor_distance": 2
        },
        {
            "id": "355933",
            "name": "Andrew Spielberg   ",
            "group": 1,
            "neighbor_number": 7,
            "neighbor_distance": 2
        },
        {
            "id": "354190",
            "name": "Sharachchandra Bhat   ",
            "group": 1,
            "neighbor_number": 7,
            "neighbor_distance": 2
        },
        {
            "id": "7851",
            "name": "Seraf   ",
            "group": 1,
            "neighbor_number": 13,
            "neighbor_distance": 3
        },
        {
            "id": "7888",
            "name": "Luc De Raedt   ",
            "group": 1,
            "neighbor_number": 11,
            "neighbor_distance": 3
        },
        {
            "id": "7799",
            "name": "Mich   ",
            "group": 1,
            "neighbor_number": 33,
            "neighbor_distance": 3
        },
        {
            "id": "7755",
            "name": "Josep Llad   ",
            "group": 1,
            "neighbor_number": 19,
            "neighbor_distance": 3
        },
        {
            "id": "7677",
            "name": "Alberto Abell   ",
            "group": 1,
            "neighbor_number": 10,
            "neighbor_distance": 3
        },
        {
            "id": "7150",
            "name": "Gerardo Fern   ",
            "group": 1,
            "neighbor_number": 6,
            "neighbor_distance": 3
        },
        {
            "id": "7179",
            "name": "Herv   ",
            "group": 1,
            "neighbor_number": 172,
            "neighbor_distance": 3
        },
        {
            "id": "7180",
            "name": "Marl   ",
            "group": 1,
            "neighbor_number": 6,
            "neighbor_distance": 3
        },
        {
            "id": "7557",
            "name": "Travis Gagie   ",
            "group": 1,
            "neighbor_number": 10,
            "neighbor_distance": 3
        },
        {
            "id": "7525",
            "name": "Miguel A. Mart   ",
            "group": 1,
            "neighbor_number": 14,
            "neighbor_distance": 3
        },
        {
            "id": "7488",
            "name": "Nicol   ",
            "group": 1,
            "neighbor_number": 120,
            "neighbor_distance": 3
        },
        {
            "id": "7231",
            "name": "Micka   ",
            "group": 1,
            "neighbor_number": 50,
            "neighbor_distance": 3
        },
        {
            "id": "7260",
            "name": "Luigi Carro   ",
            "group": 1,
            "neighbor_number": 19,
            "neighbor_distance": 3
        },
        {
            "id": "569769",
            "name": "Bruce A. Barton   ",
            "group": 1,
            "neighbor_number": 14,
            "neighbor_distance": 3
        },
        {
            "id": "53834",
            "name": "Paulo Martins Engel   ",
            "group": 1,
            "neighbor_number": 8,
            "neighbor_distance": 3
        },
        {
            "id": "8943",
            "name": "Daniel L   ",
            "group": 1,
            "neighbor_number": 10,
            "neighbor_distance": 3
        },
        {
            "id": "9734",
            "name": "Ugo Montanari   ",
            "group": 1,
            "neighbor_number": 8,
            "neighbor_distance": 3
        },
        {
            "id": "9638",
            "name": "Am   ",
            "group": 1,
            "neighbor_number": 42,
            "neighbor_distance": 3
        },
        {
            "id": "9417",
            "name": "Tinne Tuytelaars   ",
            "group": 1,
            "neighbor_number": 18,
            "neighbor_distance": 3
        },
        {
            "id": "9464",
            "name": "Davide Scaramuzza 0001   ",
            "group": 1,
            "neighbor_number": 13,
            "neighbor_distance": 3
        },
        {
            "id": "9963",
            "name": "Ales Leonardis   ",
            "group": 1,
            "neighbor_number": 43,
            "neighbor_distance": 3
        },
        {
            "id": "9919",
            "name": "Roland Siegwart   ",
            "group": 1,
            "neighbor_number": 32,
            "neighbor_distance": 3
        },
        {
            "id": "9872",
            "name": "Pablo Garc   ",
            "group": 1,
            "neighbor_number": 25,
            "neighbor_distance": 3
        },
        {
            "id": "411265",
            "name": "Mattia Petrolo   ",
            "group": 1,
            "neighbor_number": 8,
            "neighbor_distance": 3
        },
        {
            "id": "9345",
            "name": "Guillermo Sapiro   ",
            "group": 1,
            "neighbor_number": 27,
            "neighbor_distance": 3
        },
        {
            "id": "154574",
            "name": "Amr E. Mohamed   ",
            "group": 1,
            "neighbor_number": 6,
            "neighbor_distance": 3
        },
        {
            "id": "9227",
            "name": "Nuria Oliver   ",
            "group": 1,
            "neighbor_number": 6,
            "neighbor_distance": 3
        },
        {
            "id": "17737",
            "name": "Estibaliz Diaz-Tena   ",
            "group": 1,
            "neighbor_number": 19,
            "neighbor_distance": 3
        },
        {
            "id": "126306",
            "name": "Inchio Lou   ",
            "group": 1,
            "neighbor_number": 10,
            "neighbor_distance": 3
        },
        {
            "id": "119809",
            "name": "Ian Reid 0001   ",
            "group": 1,
            "neighbor_number": 14,
            "neighbor_distance": 3
        },
        {
            "id": "22291",
            "name": "Zhi-Hong Deng   ",
            "group": 1,
            "neighbor_number": 10,
            "neighbor_distance": 3
        },
        {
            "id": "54520",
            "name": "Jitender Kumar Chhabra   ",
            "group": 1,
            "neighbor_number": 8,
            "neighbor_distance": 3
        },
        {
            "id": "120940",
            "name": "Raihan Uddin Ahmed   ",
            "group": 1,
            "neighbor_number": 13,
            "neighbor_distance": 3
        },
        {
            "id": "418120",
            "name": "Kristy Elizabeth Boyer   ",
            "group": 1,
            "neighbor_number": 8,
            "neighbor_distance": 3
        },
        {
            "id": "417519",
            "name": "Victor Acu   ",
            "group": 1,
            "neighbor_number": 6,
            "neighbor_distance": 3
        },
        {
            "id": "977438",
            "name": "Hassna Irzan   ",
            "group": 1,
            "neighbor_number": 9,
            "neighbor_distance": 3
        },
        {
            "id": "252744",
            "name": "Hyungjoo Cho   ",
            "group": 1,
            "neighbor_number": 10,
            "neighbor_distance": 3
        },
        {
            "id": "419155",
            "name": "Esra Akbas   ",
            "group": 1,
            "neighbor_number": 10,
            "neighbor_distance": 3
        },
        {
            "id": "156850",
            "name": "Janez Kranjc   ",
            "group": 1,
            "neighbor_number": 14,
            "neighbor_distance": 3
        },
        {
            "id": "54213",
            "name": "Guilherme Vilar   ",
            "group": 1,
            "neighbor_number": 14,
            "neighbor_distance": 3
        },
        {
            "id": "171911",
            "name": "Runcai Huang   ",
            "group": 1,
            "neighbor_number": 9,
            "neighbor_distance": 3
        },
        {
            "id": "418629",
            "name": "Eric E. Aubanel   ",
            "group": 1,
            "neighbor_number": 9,
            "neighbor_distance": 3
        },
        {
            "id": "171529",
            "name": "Meysam Azimian   ",
            "group": 1,
            "neighbor_number": 6,
            "neighbor_distance": 3
        },
        {
            "id": "877049",
            "name": "Gustavo S. Viana   ",
            "group": 1,
            "neighbor_number": 6,
            "neighbor_distance": 3
        },
        {
            "id": "70004",
            "name": "Tony Van Gestel   ",
            "group": 1,
            "neighbor_number": 7,
            "neighbor_distance": 3
        },
        {
            "id": "70006",
            "name": "Joao Garcia   ",
            "group": 1,
            "neighbor_number": 11,
            "neighbor_distance": 3
        },
        {
            "id": "70925",
            "name": "Heshan Sun   ",
            "group": 1,
            "neighbor_number": 25,
            "neighbor_distance": 3
        },
        {
            "id": "70451",
            "name": "Shan Wang 0006   ",
            "group": 1,
            "neighbor_number": 12,
            "neighbor_distance": 3
        },
        {
            "id": "57621",
            "name": "Anne E. Haxthausen   ",
            "group": 1,
            "neighbor_number": 6,
            "neighbor_distance": 3
        },
        {
            "id": "71602",
            "name": "Cheng-Han Wu   ",
            "group": 1,
            "neighbor_number": 40,
            "neighbor_distance": 3
        },
        {
            "id": "209673",
            "name": "Martian Mot   ",
            "group": 1,
            "neighbor_number": 8,
            "neighbor_distance": 3
        },
        {
            "id": "72659",
            "name": "Piotr Zielniewicz   ",
            "group": 1,
            "neighbor_number": 8,
            "neighbor_distance": 3
        },
        {
            "id": "72662",
            "name": "Ying Hua   ",
            "group": 1,
            "neighbor_number": 9,
            "neighbor_distance": 3
        },
        {
            "id": "72251",
            "name": "Fouad Riane   ",
            "group": 1,
            "neighbor_number": 7,
            "neighbor_distance": 3
        },
        {
            "id": "375021",
            "name": "Jakob Juul Larsen   ",
            "group": 1,
            "neighbor_number": 22,
            "neighbor_distance": 3
        },
        {
            "id": "14003",
            "name": "Luk   ",
            "group": 1,
            "neighbor_number": 79,
            "neighbor_distance": 3
        },
        {
            "id": "527453",
            "name": "Yongmei Liu 0008   ",
            "group": 1,
            "neighbor_number": 6,
            "neighbor_distance": 3
        },
        {
            "id": "77495",
            "name": "Kunhe Yang   ",
            "group": 1,
            "neighbor_number": 43,
            "neighbor_distance": 3
        },
        {
            "id": "73547",
            "name": "Krishnamurthy S. Raman   ",
            "group": 1,
            "neighbor_number": 6,
            "neighbor_distance": 3
        },
        {
            "id": "74727",
            "name": "Thin Nguyen   ",
            "group": 1,
            "neighbor_number": 24,
            "neighbor_distance": 3
        },
        {
            "id": "633421",
            "name": "Jean-Paul van Oosten   ",
            "group": 1,
            "neighbor_number": 23,
            "neighbor_distance": 3
        },
        {
            "id": "50666",
            "name": "Daniel Pons Betri   ",
            "group": 1,
            "neighbor_number": 8,
            "neighbor_distance": 3
        },
        {
            "id": "74704",
            "name": "Hojung Shin   ",
            "group": 1,
            "neighbor_number": 12,
            "neighbor_distance": 3
        },
        {
            "id": "119283",
            "name": "Michael I. Friswell   ",
            "group": 1,
            "neighbor_number": 8,
            "neighbor_distance": 3
        }
    ],
    "links": [
        {
            "source": "495623",
            "target": "495625"
        },
        {
            "source": "9928",
            "target": "495623"
        },
        {
            "source": "317470",
            "target": "495623"
        },
        {
            "source": "9928",
            "target": "495625"
        },
        {
            "source": "317470",
            "target": "495625"
        },
        {
            "source": "495625",
            "target": "2759896"
        },
        {
            "source": "495625",
            "target": "1842131"
        },
        {
            "source": "495625",
            "target": "1025197"
        },
        {
            "source": "495625",
            "target": "1022134"
        },
        {
            "source": "794",
            "target": "9928"
        },
        {
            "source": "9928",
            "target": "1022134"
        },
        {
            "source": "9928",
            "target": "1866710"
        },
        {
            "source": "9928",
            "target": "2759896"
        },
        {
            "source": "9928",
            "target": "959734"
        },
        {
            "source": "9928",
            "target": "401461"
        },
        {
            "source": "9928",
            "target": "2142075"
        },
        {
            "source": "9928",
            "target": "401460"
        },
        {
            "source": "9928",
            "target": "2142074"
        },
        {
            "source": "9928",
            "target": "3158208"
        },
        {
            "source": "9928",
            "target": "2142073"
        },
        {
            "source": "9928",
            "target": "1068244"
        },
        {
            "source": "9928",
            "target": "2068750"
        },
        {
            "source": "9928",
            "target": "2617379"
        },
        {
            "source": "9928",
            "target": "2142072"
        },
        {
            "source": "9928",
            "target": "214702"
        },
        {
            "source": "9928",
            "target": "355682"
        },
        {
            "source": "9928",
            "target": "2142071"
        },
        {
            "source": "9928",
            "target": "2811112"
        },
        {
            "source": "9884",
            "target": "9928"
        },
        {
            "source": "9928",
            "target": "1842202"
        },
        {
            "source": "9928",
            "target": "317470"
        },
        {
            "source": "9928",
            "target": "498011"
        },
        {
            "source": "9928",
            "target": "117194"
        },
        {
            "source": "9928",
            "target": "545381"
        },
        {
            "source": "9928",
            "target": "354617"
        },
        {
            "source": "9928",
            "target": "1022035"
        },
        {
            "source": "9928",
            "target": "1842131"
        },
        {
            "source": "9928",
            "target": "1761990"
        },
        {
            "source": "9928",
            "target": "1866712"
        },
        {
            "source": "9928",
            "target": "355933"
        },
        {
            "source": "9928",
            "target": "354190"
        },
        {
            "source": "9928",
            "target": "1025197"
        },
        {
            "source": "317470",
            "target": "2759896"
        },
        {
            "source": "317470",
            "target": "401460"
        },
        {
            "source": "794",
            "target": "317470"
        },
        {
            "source": "317470",
            "target": "1842131"
        },
        {
            "source": "214702",
            "target": "317470"
        },
        {
            "source": "317470",
            "target": "1866710"
        },
        {
            "source": "317470",
            "target": "1022134"
        },
        {
            "source": "317470",
            "target": "1025197"
        },
        {
            "source": "9884",
            "target": "317470"
        },
        {
            "source": "317470",
            "target": "2142073"
        },
        {
            "source": "317470",
            "target": "2142072"
        },
        {
            "source": "317470",
            "target": "2142075"
        },
        {
            "source": "317470",
            "target": "2142074"
        },
        {
            "source": "317470",
            "target": "355682"
        },
        {
            "source": "317470",
            "target": "1866712"
        },
        {
            "source": "317470",
            "target": "2142071"
        },
        {
            "source": "1025197",
            "target": "2759896"
        },
        {
            "source": "1842131",
            "target": "2759896"
        },
        {
            "source": "1022134",
            "target": "2759896"
        },
        {
            "source": "1025197",
            "target": "1842131"
        },
        {
            "source": "1022134",
            "target": "1842131"
        },
        {
            "source": "1022134",
            "target": "1025197"
        },
        {
            "source": "545381",
            "target": "1022134"
        },
        {
            "source": "117194",
            "target": "1022134"
        },
        {
            "source": "794",
            "target": "7851"
        },
        {
            "source": "794",
            "target": "7888"
        },
        {
            "source": "794",
            "target": "7799"
        },
        {
            "source": "794",
            "target": "7755"
        },
        {
            "source": "794",
            "target": "7677"
        },
        {
            "source": "794",
            "target": "7150"
        },
        {
            "source": "794",
            "target": "7179"
        },
        {
            "source": "794",
            "target": "7180"
        },
        {
            "source": "794",
            "target": "7557"
        },
        {
            "source": "794",
            "target": "7525"
        },
        {
            "source": "794",
            "target": "7488"
        },
        {
            "source": "794",
            "target": "7231"
        },
        {
            "source": "794",
            "target": "7260"
        },
        {
            "source": "794",
            "target": "569769"
        },
        {
            "source": "794",
            "target": "53834"
        },
        {
            "source": "794",
            "target": "8943"
        },
        {
            "source": "794",
            "target": "9734"
        },
        {
            "source": "794",
            "target": "9638"
        },
        {
            "source": "794",
            "target": "9417"
        },
        {
            "source": "794",
            "target": "9464"
        },
        {
            "source": "794",
            "target": "9963"
        },
        {
            "source": "794",
            "target": "9919"
        },
        {
            "source": "794",
            "target": "9872"
        },
        {
            "source": "794",
            "target": "9884"
        },
        {
            "source": "794",
            "target": "411265"
        },
        {
            "source": "794",
            "target": "9345"
        },
        {
            "source": "794",
            "target": "154574"
        },
        {
            "source": "794",
            "target": "9227"
        },
        {
            "source": "794",
            "target": "17737"
        },
        {
            "source": "794",
            "target": "126306"
        },
        {
            "source": "794",
            "target": "119809"
        },
        {
            "source": "794",
            "target": "22291"
        },
        {
            "source": "794",
            "target": "54520"
        },
        {
            "source": "794",
            "target": "120940"
        },
        {
            "source": "794",
            "target": "418120"
        },
        {
            "source": "794",
            "target": "417519"
        },
        {
            "source": "794",
            "target": "977438"
        },
        {
            "source": "794",
            "target": "252744"
        },
        {
            "source": "794",
            "target": "419155"
        },
        {
            "source": "794",
            "target": "156850"
        },
        {
            "source": "794",
            "target": "54213"
        },
        {
            "source": "794",
            "target": "171911"
        },
        {
            "source": "794",
            "target": "418629"
        },
        {
            "source": "794",
            "target": "355682"
        },
        {
            "source": "794",
            "target": "171529"
        },
        {
            "source": "794",
            "target": "877049"
        },
        {
            "source": "794",
            "target": "70004"
        },
        {
            "source": "794",
            "target": "70006"
        },
        {
            "source": "794",
            "target": "70925"
        },
        {
            "source": "794",
            "target": "70451"
        },
        {
            "source": "794",
            "target": "57621"
        },
        {
            "source": "794",
            "target": "71602"
        },
        {
            "source": "794",
            "target": "209673"
        },
        {
            "source": "794",
            "target": "72659"
        },
        {
            "source": "794",
            "target": "72662"
        },
        {
            "source": "794",
            "target": "72251"
        },
        {
            "source": "794",
            "target": "375021"
        },
        {
            "source": "794",
            "target": "14003"
        },
        {
            "source": "794",
            "target": "527453"
        },
        {
            "source": "794",
            "target": "77495"
        },
        {
            "source": "794",
            "target": "73547"
        },
        {
            "source": "794",
            "target": "74727"
        },
        {
            "source": "794",
            "target": "633421"
        },
        {
            "source": "794",
            "target": "50666"
        },
        {
            "source": "794",
            "target": "74704"
        },
        {
            "source": "794",
            "target": "119283"
        },
        {
            "source": "794",
            "target": "354190"
        },
        {
            "source": "1866710",
            "target": "2142071"
        },
        {
            "source": "1866710",
            "target": "1866712"
        },
        {
            "source": "1866710",
            "target": "2142075"
        },
        {
            "source": "1866710",
            "target": "2142072"
        },
        {
            "source": "1866710",
            "target": "2142073"
        },
        {
            "source": "1866710",
            "target": "2142074"
        },
        {
            "source": "959734",
            "target": "2617379"
        },
        {
            "source": "959734",
            "target": "1761990"
        },
        {
            "source": "498011",
            "target": "959734"
        },
        {
            "source": "959734",
            "target": "2068750"
        },
        {
            "source": "117194",
            "target": "959734"
        },
        {
            "source": "959734",
            "target": "3158208"
        },
        {
            "source": "959734",
            "target": "2811112"
        },
        {
            "source": "401460",
            "target": "401461"
        },
        {
            "source": "401461",
            "target": "2068750"
        },
        {
            "source": "117194",
            "target": "401461"
        },
        {
            "source": "2142073",
            "target": "2142075"
        },
        {
            "source": "1866712",
            "target": "2142075"
        },
        {
            "source": "2142074",
            "target": "2142075"
        },
        {
            "source": "354617",
            "target": "401460"
        },
        {
            "source": "401460",
            "target": "2068750"
        },
        {
            "source": "9884",
            "target": "401460"
        },
        {
            "source": "401460",
            "target": "1068244"
        },
        {
            "source": "355933",
            "target": "401460"
        },
        {
            "source": "117194",
            "target": "401460"
        },
        {
            "source": "401460",
            "target": "1842202"
        },
        {
            "source": "401460",
            "target": "1022035"
        },
        {
            "source": "2142073",
            "target": "2142074"
        },
        {
            "source": "1866712",
            "target": "2142074"
        },
        {
            "source": "2617379",
            "target": "3158208"
        },
        {
            "source": "2068750",
            "target": "3158208"
        },
        {
            "source": "2811112",
            "target": "3158208"
        },
        {
            "source": "117194",
            "target": "3158208"
        },
        {
            "source": "1761990",
            "target": "3158208"
        },
        {
            "source": "498011",
            "target": "3158208"
        },
        {
            "source": "1866712",
            "target": "2142073"
        },
        {
            "source": "2142071",
            "target": "2142073"
        },
        {
            "source": "2142072",
            "target": "2142073"
        },
        {
            "source": "9884",
            "target": "1068244"
        },
        {
            "source": "355933",
            "target": "1068244"
        },
        {
            "source": "354617",
            "target": "1068244"
        },
        {
            "source": "1068244",
            "target": "1842202"
        },
        {
            "source": "1022035",
            "target": "1068244"
        },
        {
            "source": "545381",
            "target": "2068750"
        },
        {
            "source": "1761990",
            "target": "2068750"
        },
        {
            "source": "498011",
            "target": "2068750"
        },
        {
            "source": "117194",
            "target": "2068750"
        },
        {
            "source": "2068750",
            "target": "2811112"
        },
        {
            "source": "2068750",
            "target": "2617379"
        },
        {
            "source": "117194",
            "target": "2617379"
        },
        {
            "source": "1761990",
            "target": "2617379"
        },
        {
            "source": "2617379",
            "target": "2811112"
        },
        {
            "source": "498011",
            "target": "2617379"
        },
        {
            "source": "1866712",
            "target": "2142072"
        },
        {
            "source": "2142071",
            "target": "2142072"
        },
        {
            "source": "214702",
            "target": "545381"
        },
        {
            "source": "9884",
            "target": "214702"
        },
        {
            "source": "1866712",
            "target": "2142071"
        },
        {
            "source": "117194",
            "target": "2811112"
        },
        {
            "source": "498011",
            "target": "2811112"
        },
        {
            "source": "1761990",
            "target": "2811112"
        },
        {
            "source": "9884",
            "target": "355933"
        },
        {
            "source": "9884",
            "target": "1842202"
        },
        {
            "source": "9884",
            "target": "1022035"
        },
        {
            "source": "9884",
            "target": "354190"
        },
        {
            "source": "9884",
            "target": "354617"
        },
        {
            "source": "1022035",
            "target": "1842202"
        },
        {
            "source": "355933",
            "target": "1842202"
        },
        {
            "source": "354617",
            "target": "1842202"
        },
        {
            "source": "498011",
            "target": "1761990"
        },
        {
            "source": "117194",
            "target": "498011"
        },
        {
            "source": "117194",
            "target": "545381"
        },
        {
            "source": "117194",
            "target": "1761990"
        },
        {
            "source": "354617",
            "target": "1022035"
        },
        {
            "source": "354617",
            "target": "355933"
        },
        {
            "source": "354190",
            "target": "354617"
        },
        {
            "source": "355933",
            "target": "1022035"
        },
        {
            "source": "7851",
            "target": "72662"
        },
        {
            "source": "7851",
            "target": "120940"
        },
        {
            "source": "7888",
            "target": "9417"
        },
        {
            "source": "7179",
            "target": "7799"
        },
        {
            "source": "7179",
            "target": "7231"
        },
        {
            "source": "7179",
            "target": "14003"
        },
        {
            "source": "7179",
            "target": "7180"
        },
        {
            "source": "7488",
            "target": "77495"
        },
        {
            "source": "9464",
            "target": "9919"
        },
        {
            "source": "411265",
            "target": "877049"
        },
        {
            "source": "70925",
            "target": "154574"
        },
        {
            "source": "22291",
            "target": "74727"
        },
        {
            "source": "70004",
            "target": "70006"
        },
        {
            "source": "70925",
            "target": "74704"
        },
        {
            "source": "74704",
            "target": "119283"
        }
    ]
}